idp_bedrock_mcp_server/__init__.py
idp_bedrock_mcp_server/main.py
idp_bedrock_mcp_server-0.1.0.dist-info/licenses/LICENSE
idp_bedrock_mcp_server-0.1.0.dist-info/METADATA
idp_bedrock_mcp_server-0.1.0.dist-info/WHEEL
idp_bedrock_mcp_server-0.1.0.dist-info/entry_points.txt
idp_bedrock_mcp_server-0.1.0.dist-info/top_level.txt
idp_bedrock_mcp_server-0.1.0.dist-info/RECORD
